{"width":512,"height":512,"scale":0.9829059829059829,"name":"aunt","imagePath":"aunt_tex.png","SubTexture":[{"x":101,"y":339,"width":115,"height":172,"name":"Bags_1"},{"x":217,"y":343,"width":130,"height":79,"name":"Bags_2"},{"x":392,"y":105,"width":25,"height":81,"name":"Bags_band1"},{"rotated":true,"x":101,"y":284,"width":127,"height":54,"name":"Bags_band2"},{"x":1,"y":3,"width":78,"height":59,"name":"Camera"},{"x":388,"y":1,"width":30,"height":29,"frameX":-34,"frameY":-34,"frameWidth":98,"frameHeight":98,"name":"FX_Energy_000"},{"x":151,"y":23,"width":50,"height":50,"frameX":-24,"frameY":-24,"frameWidth":98,"frameHeight":98,"name":"FX_Energy_002"},{"x":418,"y":122,"width":70,"height":68,"frameX":-14,"frameY":-15,"frameWidth":98,"frameHeight":98,"name":"FX_Energy_004"},{"rotated":true,"x":332,"y":187,"width":78,"height":80,"frameX":-9,"frameY":-10,"frameWidth":98,"frameHeight":98,"name":"FX_Energy_006"},{"x":309,"y":104,"width":82,"height":82,"frameX":-8,"frameY":-8,"frameWidth":98,"frameHeight":98,"name":"FX_Energy_008"},{"x":411,"y":191,"width":82,"height":80,"frameX":-8,"frameY":-9,"frameWidth":98,"frameHeight":98,"name":"FX_Energy_010"},{"x":309,"y":25,"width":78,"height":78,"frameX":-10,"frameY":-10,"frameWidth":98,"frameHeight":98,"name":"FX_Energy_012"},{"x":80,"y":7,"width":70,"height":66,"frameX":-14,"frameY":-16,"frameWidth":98,"frameHeight":98,"name":"FX_Energy_014"},{"x":359,"y":424,"width":141,"height":87,"name":"Hat_1_PhotoMan"},{"x":217,"y":423,"width":141,"height":88,"name":"Hat_2"},{"x":446,"y":272,"width":65,"height":103,"name":"L_arm"},{"rotated":true,"x":359,"y":376,"width":137,"height":47,"name":"L_armup_stand"},{"x":281,"y":13,"width":27,"height":57,"name":"L_hand"},{"x":501,"y":446,"width":10,"height":65,"name":"Line_camera"},{"rotated":true,"x":418,"y":102,"width":70,"height":19,"name":"Ling_camera2"},{"x":353,"y":279,"width":92,"height":96,"name":"Moustache"},{"rotated":true,"x":489,"y":108,"width":19,"height":58,"name":"MoustacheUP"},{"x":388,"y":49,"width":43,"height":52,"name":"R_arm"},{"rotated":true,"x":108,"y":74,"width":115,"height":88,"name":"R_armup_happy"},{"rotated":true,"x":229,"y":268,"width":123,"height":74,"name":"R_armup_stand"},{"x":224,"y":71,"width":84,"height":115,"name":"R_armup_stand2"},{"rotated":true,"x":202,"y":12,"width":78,"height":58,"name":"R_sleeve"},{"x":432,"y":68,"width":55,"height":13,"name":"brow1"},{"x":432,"y":82,"width":53,"height":19,"name":"brow2"},{"x":309,"y":1,"width":51,"height":23,"name":"brow3"},{"rotated":true,"x":494,"y":216,"width":17,"height":55,"name":"brow4"},{"x":73,"y":87,"width":34,"height":192,"name":"clothes1"},{"x":1,"y":63,"width":71,"height":216,"name":"clothes2"},{"x":1,"y":280,"width":99,"height":231,"name":"clothes3"},{"x":151,"y":6,"width":48,"height":16,"name":"eye1"},{"rotated":true,"x":494,"y":167,"width":17,"height":48,"name":"eye2"},{"x":388,"y":31,"width":46,"height":17,"name":"eye3"},{"x":432,"y":50,"width":48,"height":17,"name":"eye4"},{"x":108,"y":163,"width":101,"height":120,"name":"face_stand"},{"x":73,"y":74,"width":21,"height":12,"name":"mouth_angry"},{"x":361,"y":8,"width":24,"height":16,"name":"mouth_happy"},{"x":210,"y":275,"width":16,"height":8,"name":"mouth_upset"},{"x":210,"y":187,"width":121,"height":80,"name":"trousers"}]}